tunnel_v4/__init__.py
tunnel_v4/cli.py
tunnel_v4/config.py
tunnel_v4/agent/__init__.py
tunnel_v4/agent/agent.py
tunnel_v4/agent/agent_v3.py
tunnel_v4/agent/cli_agent.py
tunnel_v4/agent/ip_info.py
tunnel_v4/agent/keep_agent.py
tunnel_v4/agent/production_agent.py
tunnel_v4/agent/system_detect.py
tunnel_v4/agent/tunnel_client.py
tunnel_v4/agent/tunnel_connection.py
tunnel_v4/agent/plugins/__init__.py
tunnel_v4/agent/plugins/base.py
tunnel_v4/agent/plugins/exec.py
tunnel_v4/agent/plugins/http_forward.py
tunnel_v4/agent/plugins/socks5.py
tunnel_v4/agent/plugins/tcp_forward.py
tunnel_v4/agent/plugins/terminal.py
tunnel_v4/agent/plugins/websocket_forward.py
tunnel_v4/client/__init__.py
tunnel_v4/client/cli_config.py
tunnel_v4/client/cli_exec.py
tunnel_v4/client/cli_service.py
tunnel_v4/client/cli_socks5.py
tunnel_v4/client/cli_tcp.py
tunnel_v4/client/cli_terminal.py
tunnel_v4/client/cli_terminal_improved.py
tunnel_v4/client/cli_v3.py
m_tunnel4-4.0.3.dist-info/METADATA
m_tunnel4-4.0.3.dist-info/WHEEL
m_tunnel4-4.0.3.dist-info/entry_points.txt
m_tunnel4-4.0.3.dist-info/top_level.txt
m_tunnel4-4.0.3.dist-info/RECORD
