Metadata-Version: 2.1
Name: m-tunnel4
Version: 4.0.3
Summary: Tunnel System V4 - Cloudflare Workers based tunnel system
Home-page: https://github.com/yourusername/tunnel-v4
Author: Tunnel System Team
License: UNKNOWN
Platform: UNKNOWN
Classifier: Development Status :: 4 - Beta
Classifier: Intended Audience :: Developers
Classifier: License :: OSI Approved :: MIT License
Classifier: Programming Language :: Python :: 3
Classifier: Programming Language :: Python :: 3.10
Classifier: Programming Language :: Python :: 3.11
Requires-Python: >=3.10
Requires-Dist: aiohttp (>=3.8.0)
Requires-Dist: click (>=8.0.0)
Requires-Dist: psutil (>=5.9.0)
Requires-Dist: requests (>=2.28.0)
Requires-Dist: websockets (>=10.0)
